{
  "wizard": {
    "fireball": {
      "speed": 450,
      "range": 1050,
      "bobAmplitude": 5,
      "bobFreqMs": 120,
      "collisionRadius": 38,
      "forwardOffset": 0.23,
      "verticalOffset": 0.12,
      "startupMs": 300,
      "ownerEcho": true
    }
  },
  "draven": {
    "splash": {
      "width": 150,
      "height": 108,
      "activeWindowMs": 450,
      "damageStartMs": 100,
      "damageTickMs": 90,
      "tipOffset": 50,
      "minHeight": 20,
      "growDurationMs": 220,
      "centerYFactor": 0.15,
      "remoteExplosionDelayMs": 500
    }
  }
}
